{
  "/__docusaurus/debug-600": {
    "__comp": "__comp---theme-debug-config-23-a-2ff",
    "__context": {
      "plugin": "plugin---docusaurus-debug-994-839"
    }
  },
  "/__docusaurus/debug/config-498": {
    "__comp": "__comp---theme-debug-config-23-a-2ff",
    "__context": {
      "plugin": "plugin---docusaurus-debug-994-839"
    }
  },
  "/__docusaurus/debug/content-b3c": {
    "__comp": "__comp---theme-debug-contentba-8-ce7",
    "__context": {
      "plugin": "plugin---docusaurus-debug-994-839"
    },
    "allContent": "allContent---docusaurus-debug-content-246-9aa"
  },
  "/__docusaurus/debug/globalData-8c3": {
    "__comp": "__comp---theme-debug-global-dataede-0fa",
    "__context": {
      "plugin": "plugin---docusaurus-debug-994-839"
    }
  },
  "/__docusaurus/debug/metadata-c83": {
    "__comp": "__comp---theme-debug-site-metadata-68-e-3d4",
    "__context": {
      "plugin": "plugin---docusaurus-debug-994-839"
    }
  },
  "/__docusaurus/debug/registry-da9": {
    "__comp": "__comp---theme-debug-registry-679-501",
    "__context": {
      "plugin": "plugin---docusaurus-debug-994-839"
    }
  },
  "/__docusaurus/debug/routes-f07": {
    "__comp": "__comp---theme-debug-routes-946-699",
    "__context": {
      "plugin": "plugin---docusaurus-debug-994-839"
    }
  },
  "/archive-460": {
    "__comp": "__comp---theme-blog-archive-page-9-e-4-1d8",
    "__context": {
      "plugin": "plugin---archived-4-b-c5b"
    },
    "archive": "archive---archive-2-e-8-25f"
  },
  "/babel-plugin-e1c": {
    "__comp": "__comp---theme-blog-post-pageccc-cab",
    "__context": {
      "plugin": "plugin---archived-4-b-c5b"
    },
    "sidebar": "sidebar---babel-plugin-814-fca",
    "content": "content---babel-pluginfdd-246"
  },
  "/css-mask-b5b": {
    "__comp": "__comp---theme-blog-post-pageccc-cab",
    "__context": {
      "plugin": "plugin---archived-4-b-c5b"
    },
    "sidebar": "sidebar---babel-plugin-814-fca",
    "content": "content---css-maskcbe-ea1"
  },
  "/electron-apps-automatically-update-e88": {
    "__comp": "__comp---theme-blog-post-pageccc-cab",
    "__context": {
      "plugin": "plugin---archived-4-b-c5b"
    },
    "sidebar": "sidebar---babel-plugin-814-fca",
    "content": "content---electron-apps-automatically-updatefe-1-621"
  },
  "/hot-vs-cold-observables-2b5": {
    "__comp": "__comp---theme-blog-post-pageccc-cab",
    "__context": {
      "plugin": "plugin---archived-4-b-c5b"
    },
    "sidebar": "sidebar---babel-plugin-814-fca",
    "content": "content---hot-vs-cold-observablesb-48-7b4"
  },
  "/react-hooks-best-practices-44b": {
    "__comp": "__comp---theme-blog-post-pageccc-cab",
    "__context": {
      "plugin": "plugin---archived-4-b-c5b"
    },
    "sidebar": "sidebar---babel-plugin-814-fca",
    "content": "content---react-hooks-best-practices-6-e-8-7a4"
  },
  "/rxjs-ipc-22b": {
    "__comp": "__comp---theme-blog-post-pageccc-cab",
    "__context": {
      "plugin": "plugin---archived-4-b-c5b"
    },
    "sidebar": "sidebar---babel-plugin-814-fca",
    "content": "content---rxjs-ipc-7-cb-381"
  },
  "/rxjs-on-the-netease-cloud-music-desktop-9f0": {
    "__comp": "__comp---theme-blog-post-pageccc-cab",
    "__context": {
      "plugin": "plugin---archived-4-b-c5b"
    },
    "sidebar": "sidebar---babel-plugin-814-fca",
    "content": "content---rxjs-on-the-netease-cloud-music-desktop-3-b-7-384"
  },
  "/sourcemap-6fa": {
    "__comp": "__comp---theme-blog-post-pageccc-cab",
    "__context": {
      "plugin": "plugin---archived-4-b-c5b"
    },
    "sidebar": "sidebar---babel-plugin-814-fca",
    "content": "content---sourcemapddd-f16"
  },
  "/tags-26c": {
    "__comp": "__comp---theme-blog-tags-list-page-01-a-d0b",
    "__context": {
      "plugin": "plugin---archived-4-b-c5b"
    },
    "sidebar": "sidebar---babel-plugin-814-fca",
    "tags": "tags---tagsc-57-e72"
  },
  "/tags/ast-bb8": {
    "__comp": "__comp---theme-blog-tags-posts-page-687-b6c",
    "__context": {
      "plugin": "plugin---archived-4-b-c5b"
    },
    "sidebar": "sidebar---babel-plugin-814-fca",
    "items": [
      {
        "content": "content---tags-astc-51-a31"
      }
    ],
    "tag": "tag---tags-ast-8-de-c77",
    "listMetadata": "listMetadata---tags-ast-5-f-5-73c"
  },
  "/tags/babel-f33": {
    "__comp": "__comp---theme-blog-tags-posts-page-687-b6c",
    "__context": {
      "plugin": "plugin---archived-4-b-c5b"
    },
    "sidebar": "sidebar---babel-plugin-814-fca",
    "items": [
      {
        "content": "content---tags-astc-51-a31"
      }
    ],
    "tag": "tag---tags-babel-184-f77",
    "listMetadata": "listMetadata---tags-babel-807-2f7"
  },
  "/tags/css-499": {
    "__comp": "__comp---theme-blog-tags-posts-page-687-b6c",
    "__context": {
      "plugin": "plugin---archived-4-b-c5b"
    },
    "sidebar": "sidebar---babel-plugin-814-fca",
    "items": [
      {
        "content": "content---tags-css-2-fe-352"
      }
    ],
    "tag": "tag---tags-css-06-a-516",
    "listMetadata": "listMetadata---tags-cssd-7-c-c29"
  },
  "/tags/electron-38c": {
    "__comp": "__comp---theme-blog-tags-posts-page-687-b6c",
    "__context": {
      "plugin": "plugin---archived-4-b-c5b"
    },
    "sidebar": "sidebar---babel-plugin-814-fca",
    "items": [
      {
        "content": "content---tags-electronf-8-f-e24"
      }
    ],
    "tag": "tag---tags-electron-61-b-d45",
    "listMetadata": "listMetadata---tags-electron-715-d97"
  },
  "/tags/hooks-e37": {
    "__comp": "__comp---theme-blog-tags-posts-page-687-b6c",
    "__context": {
      "plugin": "plugin---archived-4-b-c5b"
    },
    "sidebar": "sidebar---babel-plugin-814-fca",
    "items": [
      {
        "content": "content---tags-hooks-1-c-2-18c"
      }
    ],
    "tag": "tag---tags-hooksb-64-933",
    "listMetadata": "listMetadata---tags-hooks-118-f4a"
  },
  "/tags/javascript-3a0": {
    "__comp": "__comp---theme-blog-tags-posts-page-687-b6c",
    "__context": {
      "plugin": "plugin---archived-4-b-c5b"
    },
    "sidebar": "sidebar---babel-plugin-814-fca",
    "items": [
      {
        "content": "content---tags-javascriptde-0-0ad"
      },
      {
        "content": "content---tags-astc-51-a31"
      },
      {
        "content": "content---tags-javascriptfda-64a"
      },
      {
        "content": "content---tags-hooks-1-c-2-18c"
      },
      {
        "content": "content---tags-javascript-424-83e"
      },
      {
        "content": "content---813-189"
      }
    ],
    "tag": "tag---tags-javascript-305-7c3",
    "listMetadata": "listMetadata---tags-javascript-350-b92"
  },
  "/tags/react-98c": {
    "__comp": "__comp---theme-blog-tags-posts-page-687-b6c",
    "__context": {
      "plugin": "plugin---archived-4-b-c5b"
    },
    "sidebar": "sidebar---babel-plugin-814-fca",
    "items": [
      {
        "content": "content---tags-hooks-1-c-2-18c"
      }
    ],
    "tag": "tag---tags-reactd-9-c-4f1",
    "listMetadata": "listMetadata---tags-react-807-301"
  },
  "/tags/rxjs-df9": {
    "__comp": "__comp---theme-blog-tags-posts-page-687-b6c",
    "__context": {
      "plugin": "plugin---archived-4-b-c5b"
    },
    "sidebar": "sidebar---babel-plugin-814-fca",
    "items": [
      {
        "content": "content---tags-javascriptfda-64a"
      },
      {
        "content": "content---tags-javascript-424-83e"
      },
      {
        "content": "content---813-189"
      }
    ],
    "tag": "tag---tags-rxjs-714-c6f",
    "listMetadata": "listMetadata---tags-rxjs-54-f-a1d"
  },
  "/tags/sourcemap-f5a": {
    "__comp": "__comp---theme-blog-tags-posts-page-687-b6c",
    "__context": {
      "plugin": "plugin---archived-4-b-c5b"
    },
    "sidebar": "sidebar---babel-plugin-814-fca",
    "items": [
      {
        "content": "content---tags-javascriptde-0-0ad"
      }
    ],
    "tag": "tag---tags-sourcemap-1-e-6-47c",
    "listMetadata": "listMetadata---tags-sourcemap-11-d-8d9"
  },
  "/-448": {
    "__comp": "__comp---theme-blog-list-pagea-6-a-7ba",
    "__context": {
      "plugin": "plugin---archived-4-b-c5b"
    },
    "sidebar": "sidebar---babel-plugin-814-fca",
    "items": [
      {
        "content": "content---tags-javascriptde-0-0ad"
      },
      {
        "content": "content---tags-astc-51-a31"
      },
      {
        "content": "content---tags-javascriptfda-64a"
      },
      {
        "content": "content---tags-electronf-8-f-e24"
      },
      {
        "content": "content---tags-hooks-1-c-2-18c"
      },
      {
        "content": "content---tags-javascript-424-83e"
      },
      {
        "content": "content---813-189"
      },
      {
        "content": "content---tags-css-2-fe-352"
      }
    ],
    "metadata": "metadata---a-55-c63"
  }
}